setup.py
lexus/__init__.py
lexus/lex_io.py
lexus/template_generator.py
lexus.egg-info/PKG-INFO
lexus.egg-info/SOURCES.txt
lexus.egg-info/dependency_links.txt
lexus.egg-info/entry_points.txt
lexus.egg-info/not-zip-safe
lexus.egg-info/top_level.txt
test/test_response.py