Metadata-Version: 1.0
Name: lexus
Version: 0.2.1
Summary: Easy development tool for AWS Lex
Home-page: https://github.com/ysak-y/lexus-test.git
Author: Yoshiaki Yamada
Author-email: yoshiaki.0614@gmail.com
License: MIT
Platform: UNKNOWN
